LICENCE
openscm_units-0.6.3.dist-info/METADATA
openscm_units-0.6.3.dist-info/WHEEL
openscm_units-0.6.3.dist-info/entry_points.txt
openscm_units-0.6.3.dist-info/licenses/LICENCE
openscm_units/__init__.py
openscm_units/_unit_registry.py
openscm_units/data/__init__.py
openscm_units/data/mixtures.py
openscm_units/py.typed
openscm_units-0.6.3.dist-info/RECORD
