Metadata-Version: 2.1
Name: openscm-units
Version: 0.6.3
Summary: Handling of units related to simple climate modelling.
Author-Email: Zebedee Nicholls <zebedee.nicholls@climate-energy-college.org>, Jared Lewis <jared.lewis@climate-resource.com>, Mika Pflueger <mika.pflueger@climate-resource.com>, Robert Gieseke <rob.g@web.de>, Sven Willner <sven.willer@gmail.com>
License: BSD-3-Clause
Classifier: License :: OSI Approved :: BSD License
Requires-Python: >=3.9
Requires-Dist: pint
Requires-Dist: globalwarmingpotentials
Requires-Dist: numpy
Requires-Dist: pandas
Provides-Extra: locked
Requires-Dist: appdirs==1.4.4; extra == "locked"
Requires-Dist: flexcache==0.3; extra == "locked"
Requires-Dist: flexparser==0.3.1; extra == "locked"
Requires-Dist: globalwarmingpotentials==0.11.1; extra == "locked"
Requires-Dist: numpy==2.0.2; extra == "locked"
Requires-Dist: pandas==2.2.3; extra == "locked"
Requires-Dist: pint==0.24.3; extra == "locked"
Requires-Dist: python-dateutil==2.9.0.post0; extra == "locked"
Requires-Dist: pytz==2024.2; extra == "locked"
Requires-Dist: six==1.16.0; extra == "locked"
Requires-Dist: typing-extensions==4.12.2; extra == "locked"
Requires-Dist: tzdata==2024.2; extra == "locked"
